utmService/__init__.py
utmService/nrid/__init__.py
utmService/nrid/nrid_service.py
utmService/nrid/qmi_rid.py
utmService/nrid/ussp/__init__.py
utmService/nrid/ussp/json_creators.py
utmService/nrid/ussp/message_security.py
utmService/nrid/ussp/network_utility_interface.py
utmService/nrid/ussp/non_repudiation.py
utmService-0.1.0.dist-info/METADATA
utmService-0.1.0.dist-info/WHEEL
utmService-0.1.0.dist-info/top_level.txt
utmService-0.1.0.dist-info/RECORD
